TabularOODBench/__init__.py
TabularOODBench/dataset.py
TabularOODBench/folktables_utils.py
TabularOODBench/test.py
TabularOODBench/utils.py
TabularOODBench/folktables/__init__.py
TabularOODBench/folktables/acs.py
TabularOODBench/folktables/dataset.py
TabularOODBench/folktables/exceptions.py
TabularOODBench/folktables/folktables.py
TabularOODBench/folktables/load_acs.py
TabularOODBench/folktables/utils/__init__.py
TabularOODBench/folktables/utils/download_utils.py
TabularOODBench/folktables/utils/files_resources.py
TabularOODBench/folktables/utils/load_utils.py
tabularoodbench/__init__.py
tabularoodbench/dataset.py
tabularoodbench/folktables_utils.py
tabularoodbench/test.py
tabularoodbench/utils.py
tabularoodbench/folktables/__init__.py
tabularoodbench/folktables/acs.py
tabularoodbench/folktables/dataset.py
tabularoodbench/folktables/exceptions.py
tabularoodbench/folktables/folktables.py
tabularoodbench/folktables/load_acs.py
tabularoodbench/folktables/utils/__init__.py
tabularoodbench/folktables/utils/download_utils.py
tabularoodbench/folktables/utils/files_resources.py
tabularoodbench/folktables/utils/load_utils.py
tabularoodbench-0.1.2.dist-info/LICENSE
tabularoodbench-0.1.2.dist-info/METADATA
tabularoodbench-0.1.2.dist-info/WHEEL
tabularoodbench-0.1.2.dist-info/top_level.txt
tabularoodbench-0.1.2.dist-info/RECORD
